mini_dust3r/__init__.py
mini_dust3r/image_pairs.py
mini_dust3r/inference.py
mini_dust3r/model.py
mini_dust3r/optim_factory.py
mini_dust3r/patch_embed.py
mini_dust3r/post_process.py
mini_dust3r/viz.py
mini_dust3r/api/__init__.py
mini_dust3r/api/inference.py
mini_dust3r/cloud_opt/__init__.py
mini_dust3r/cloud_opt/base_opt.py
mini_dust3r/cloud_opt/commons.py
mini_dust3r/cloud_opt/init_im_poses.py
mini_dust3r/cloud_opt/modular_optimizer.py
mini_dust3r/cloud_opt/optimizer.py
mini_dust3r/cloud_opt/pair_viewer.py
mini_dust3r/croco/blocks.py
mini_dust3r/croco/croco.py
mini_dust3r/croco/dpt_block.py
mini_dust3r/croco/masking.py
mini_dust3r/croco/pos_embed.py
mini_dust3r/gradio_ui/dust3r_ui.py
mini_dust3r/heads/__init__.py
mini_dust3r/heads/dpt_head.py
mini_dust3r/heads/linear_head.py
mini_dust3r/heads/postprocess.py
mini_dust3r/utils/device.py
mini_dust3r/utils/geometry.py
mini_dust3r/utils/image.py
mini_dust3r/utils/misc.py
mini_dust3r-0.1.2.dist-info/LICENSE
mini_dust3r-0.1.2.dist-info/METADATA
mini_dust3r-0.1.2.dist-info/WHEEL
mini_dust3r-0.1.2.dist-info/top_level.txt
mini_dust3r-0.1.2.dist-info/RECORD
