Metadata-Version: 2.1
Name: mini-dust3r
Version: 0.1.2
Summary: Miniature version of dust3r, focused on inference
License: DUSt3R, Copyright (c) 2024-present Naver Corporation, is licensed under the Creative Commons Attribution-NonCommercial-ShareAlike 4.0 license.
Classifier: Development Status :: 3 - Alpha
Classifier: Programming Language :: Python
Requires-Python: >=3.10.0
License-File: LICENSE
Requires-Dist: torch >=2.3.1
Requires-Dist: torchvision >=0.18.1
Requires-Dist: opencv-python >=4.10.0
Requires-Dist: rerun-sdk >=0.17.0
Requires-Dist: tqdm >=4.66.5
Requires-Dist: trimesh >=4.4.4
Requires-Dist: jaxtyping >=0.2.33
Requires-Dist: beartype >=0.18.5
Requires-Dist: einops >=0.8.0
Requires-Dist: gradio >=4.41.0
Requires-Dist: scipy >=1.14.0
Requires-Dist: roma >=1.5
Requires-Dist: safetensors >=0.4.3
Requires-Dist: hf-transfer >=0.1.6
Requires-Dist: gradio-rerun <0.0.5,>=0.0.4
